systemdata/__init__.py
systemdata/ms.py
msSysCtl-0.0.1.dist-info/LICENCE
msSysCtl-0.0.1.dist-info/METADATA
msSysCtl-0.0.1.dist-info/WHEEL
msSysCtl-0.0.1.dist-info/top_level.txt
msSysCtl-0.0.1.dist-info/RECORD
