Metadata-Version: 2.1
Name: msSysCtl
Version: 0.0.1
Summary: In this pakage used to get system informations and control your system volumes and sound
Author: Mari Selvam B
Author-email: Mari Selvam B <mariselvam@kloudping.com>
Project-URL: Homepage, https://github.com/Mariselvam-B/msSysCtl
Project-URL: Bug Tracker, https://github.com/Mariselvam-B/msSysCtl
Classifier: Programming Language :: Python :: 3
Classifier: License :: OSI Approved :: MIT License
Classifier: Operating System :: OS Independent
Requires-Python: >=3.7
License-File: LICENCE
